[
{
  "school": "University of Hawaii at Manoa",
  "num": "CIS 705",
  "level": "Graduate",
  "title": "Data Science Foundations",
  "url": "http://lipyeow.github.io/cis705f18",
  "semester": "Fall",
  "year": 2018
},
{
  "school": "University of Hawaii at Manoa",
  "num": "ICS 691E",
  "level": "Graduate",
  "title": "Data Science Foundations",
  "url": "http://lipyeow.github.io/cis705f18",
  "semester": "Fall",
  "year": 2018
},
{
  "school": "University of Hawaii at Manoa",
  "num": "ICS 491",
  "level": "Undergraduate",
  "title": "Special Topics - Big Data Analytics",
  "url": "http://lipyeow.github.io/ics491f17",
  "semester": "Fall",
  "year": 2017
},
{
  "school": "University of Hawaii at Manoa",
  "num": "ICS 321",
  "level": "Undergraduate",
  "title": "Database Systems I",
  "url": "http://lipyeow.github.io/ics321s18",
  "semester": "Spring",
  "year": 2018
},
{
  "school": "University of Hawaii at Manoa",
  "num": "ICS 321",
  "level": "Undergraduate",
  "title": "Database Systems I",
  "url": "https://lipyeow.github.io/home/teaching/ics321/2009fall/",
  "semester": "Fall",
  "year": 2009
},
{
  "school": "University of Hawaii at Manoa",
  "num": "ICS 321",
  "level": "Undergraduate",
  "title": "Database Systems I",
  "url": "https://lipyeow.github.io/home/teaching/ics321/2010fall/",
  "semester": "Fall",
  "year": 2010
},
{
  "school": "University of Hawaii at Manoa",
  "num": "ICS 321",
  "level": "Undergraduate",
  "title": "Database Systems I",
  "url": "https://lipyeow.github.io/home/teaching/ics321/2011spr/",
  "semester": "Spring",
  "year": 2011
},
{
  "school": "University of Hawaii at Manoa",
  "num": "ICS 321",
  "level": "Undergraduate",
  "title": "Database Systems I",
  "url": "https://lipyeow.github.io/home/teaching/ics321/2011fall/",
  "semester": "Fall",
  "year": 2011
},
{
  "school": "University of Hawaii at Manoa",
  "num": "ICS 321",
  "level": "Undergraduate",
  "title": "Database Systems I",
  "url": "https://lipyeow.github.io/home/teaching/ics321/2012spr/",
  "semester": "Spring",
  "year": 2012
},
{
  "school": "University of Hawaii at Manoa",
  "num": "ICS 321",
  "level": "Undergraduate",
  "title": "Database Systems I",
  "url": "https://lipyeow.github.io/home/teaching/ics321/2012fall/",
  "semester": "Fall",
  "year": 2012
},
{
  "school": "University of Hawaii at Manoa",
  "num": "ICS 321",
  "level": "Undergraduate",
  "title": "Database Systems I",
  "url": "https://lipyeow.github.io/home/teaching/ics321/2013spr/",
  "semester": "Spring",
  "year": 2013
},
{
  "school": "University of Hawaii at Manoa",
  "num": "ICS 321",
  "level": "Undergraduate",
  "title": "Database Systems I",
  "url": "https://lipyeow.github.io/home/teaching/ics321/2013fall/",
  "semester": "Fall",
  "year": 2013
},
{
  "school": "University of Hawaii at Manoa",
  "num": "ICS 321",
  "level": "Undergraduate",
  "title": "Database Systems I",
  "url": "https://lipyeow.github.io/home/teaching/ics321/2014spr/",
  "semester": "Spring",
  "year": 2014
},
{
  "school": "University of Hawaii at Manoa",
  "num": "ICS 321",
  "level": "Undergraduate",
  "title": "Database Systems I",
  "url": "https://lipyeow.github.io/home/teaching/ics321/2014fall/",
  "semester": "Fall",
  "year": 2014
},
{
  "school": "University of Hawaii at Manoa",
  "num": "ICS 321",
  "level": "Undergraduate",
  "title": "Database Systems I",
  "url": "https://lipyeow.github.io/home/teaching/ics321/2015spr/",
  "semester": "Spring",
  "year": 2015
},
{
  "school": "University of Hawaii at Manoa",
  "num": "ICS 321",
  "level": "Undergraduate",
  "title": "Database Systems I",
  "url": "https://lipyeow.github.io/home/teaching/ics321/2015fall/",
  "semester": "Fall",
  "year": 2015
},
{
  "school": "University of Hawaii at Manoa",
  "num": "ICS 321",
  "level": "Undergraduate",
  "title": "Database Systems I",
  "url": "http://lipyeow.github.io/ics321f16",
  "semester": "Fall",
  "year": 2016
},
{
  "school": "University of Hawaii at Manoa",
  "num": "ICS 421",
  "level": "Undergraduate",
  "title": "Database Systems  II",
  "url": "http://lipyeow.github.io/ics421s18",
  "semester": "Spring",
  "year": 2018
},
{
  "school": "University of Hawaii at Manoa",
  "num": "ICS 421",
  "level": "Undergraduate",
  "title": "Database Systems  II",
  "url": "https://lipyeow.github.io/home/teaching/ics421/2010spr/",
  "semester": "Spring",
  "year": 2010
},
{
  "school": "University of Hawaii at Manoa",
  "num": "ICS 421",
  "level": "Undergraduate",
  "title": "Database Systems  II",
  "url": "http://lipyeow.github.io/ics421s17",
  "semester": "Spring",
  "year": 2017
},
{
  "school": "University of Hawaii at Manoa",
  "num": "ICS 101",
  "level": "Undergraduate",
  "title": "Tools for the Information Age",
  "url": "https://lipyeow.github.io/home/teaching/ics101/2010spr/",
  "semester": "Spring",
  "year": 2010
},
{
  "school": "University of Hawaii at Manoa",
  "num": "ICS 101",
  "level": "Undergraduate",
  "title": "Tools for the Information Age",
  "url": "https://lipyeow.github.io/home/teaching/ics101/2011fall/",
  "semester": "Fall",
  "year": 2011
},
{
  "school": "University of Hawaii at Manoa",
  "num": "ICS 101",
  "level": "Undergraduate",
  "title": "Tools for the Information Age",
  "url": "https://lipyeow.github.io/home/teaching/ics101/2012fall/",
  "semester": "Fall",
  "year": 2012
},
{
  "school": "University of Hawaii at Manoa",
  "num": "ICS 101",
  "level": "Undergraduate",
  "title": "Tools for the Information Age",
  "url": "https://lipyeow.github.io/home/teaching/ics101/2013fall/",
  "semester": "Fall",
  "year": 2013
},
{
  "school": "University of Hawaii at Manoa",
  "num": "ICS 101",
  "level": "Undergraduate",
  "title": "Tools for the Information Age",
  "url": "https://lipyeow.github.io/home/teaching/ics101/2014fall/",
  "semester": "Fall",
  "year": 2014
},
{
  "school": "University of Hawaii at Manoa",
  "num": "ICS 101",
  "level": "Undergraduate",
  "title": "Tools for the Information Age",
  "url": "https://lipyeow.github.io/home/teaching/ics101/2016spr/",
  "semester": "Spring",
  "year": 2016
},
{
  "school": "University of Hawaii at Manoa",
  "num": "ICS 101",
  "level": "Undergraduate",
  "title": "Tools for the Information Age",
  "url": "https://lipyeow.github.io/home/teaching/ics101/2017spr/",
  "semester": "Spring",
  "year": 2017
},
{
  "school": "University of Hawaii at Manoa",
  "num": "ICS 101",
  "level": "Undergraduate",
  "title": "Tools for the Information Age",
  "url": "https://lipyeow.github.io/home/teaching/ics101/2017fall/",
  "semester": "Fall",
  "year": 2017
},
{
  "school": "University of Hawaii at Manoa",
  "num": "ICS 621",
  "level": "Graduate",
  "title": "Analysis of Algorithms",
  "url": "https://lipyeow.github.io/home/teaching/ics621/2012spr/",
  "semester": "Spring",
  "year": 2012
},
{
  "school": "University of Hawaii at Manoa",
  "num": "ICS 621",
  "level": "Graduate",
  "title": "Analysis of Algorithms",
  "url": "https://lipyeow.github.io/home/teaching/ics621/2014spr/",
  "semester": "Spring",
  "year": 2014
},
{
  "school": "University of Hawaii at Manoa",
  "num": "ICS 621",
  "level": "Graduate",
  "title": "Analysis of Algorithms",
  "url": "https://lipyeow.github.io/home/teaching/ics621/2015fall/",
  "semester": "Fall",
  "year": 2015
},
{
  "school": "University of Hawaii at Manoa",
  "num": "ICS 621",
  "level": "Graduate",
  "title": "Analysis of Algorithms",
  "url": "http://lipyeow.github.io/ics621f17",
  "semester": "Fall",
  "year": 2017
},
{
  "school": "University of Hawaii at Manoa",
  "num": "ICS 624",
  "level": "Graduate",
  "title": "Advance Data Management",
  "url": "https://lipyeow.github.io/home/teaching/ics624/2015spr/",
  "semester": "Spring",
  "year": 2015
},
{
  "school": "University of Hawaii at Manoa",
  "num": "ICS 624",
  "level": "Graduate",
  "title": "Advance Data Management",
  "url": "https://lipyeow.github.io/home/teaching/ics624/2011spr/",
  "semester": "Spring",
  "year": 2011
},
{
  "school": "University of Hawaii at Manoa",
  "num": "ICS 624",
  "level": "Graduate",
  "title": "Advance Data Management",
  "url": "https://lipyeow.github.io/home/teaching/ics624/2013spr/",
  "semester": "Spring",
  "year": 2013
}
]
